helpers/config.json
main/__init__.py
main/main.py
repo2txt-0.1.6.dist-info/LICENSE
repo2txt-0.1.6.dist-info/METADATA
repo2txt-0.1.6.dist-info/WHEEL
repo2txt-0.1.6.dist-info/entry_points.txt
repo2txt-0.1.6.dist-info/top_level.txt
repo2txt-0.1.6.dist-info/RECORD
