Metadata-Version: 2.1
Name: repo2txt
Version: 0.1.6
Summary: A tool for combining the structure and contents of software repositories into a single file.
Author-email: Jack Krosinski <jack.krosinski@oceidon.com>
Maintainer-email: Jack Krosinski <jack.krosinski@oceidon.com>
License: MIT License
Project-URL: Homepage, https://github.com/donoceidon/repo2txt
Project-URL: Issues, https://github.com/donoceidon/repo2txt/issues
Keywords: gpt,training,combine
Classifier: Programming Language :: Python :: 3
Classifier: License :: OSI Approved :: MIT License
Classifier: Operating System :: OS Independent
Requires-Python: >=3.8
License-File: LICENSE
Requires-Dist: python-docx>=0.8.10
